honeybee_idaice/__init__.py
honeybee_idaice/__main__.py
honeybee_idaice/_extend_honeybee.py
honeybee_idaice/archive.py
honeybee_idaice/bldgbody.py
honeybee_idaice/face.py
honeybee_idaice/shade.py
honeybee_idaice/writer.py
honeybee_idaice/writer_obj.py
honeybee_idaice/cli/__init__.py
honeybee_idaice/cli/translate.py
honeybee_idaice/properties/__init__.py
honeybee_idaice/properties/model.py
honeybee_idaice/templates/ahu.idc
honeybee_idaice/templates/ahu.idm
honeybee_idaice/templates/building.idm
honeybee_idaice/templates/electrical system.idm
honeybee_idaice/templates/plant.idm
honeybee_idaice/templates/room.idm
honeybee_idaice-1.3.0.dist-info/licenses/LICENSE
honeybee_idaice-1.3.0.dist-info/METADATA
honeybee_idaice-1.3.0.dist-info/WHEEL
honeybee_idaice-1.3.0.dist-info/entry_points.txt
honeybee_idaice-1.3.0.dist-info/top_level.txt
honeybee_idaice-1.3.0.dist-info/RECORD
